my_first_python_package_cdelacombaz/__init__.py
my_first_python_package_cdelacombaz/bubble_sort.py
my_first_python_package_cdelacombaz/insertion_sort.py
my_first_python_package_cdelacombaz/quick_sort.py
my_first_python_package_cdelacombaz/selection_sort.py
my_first_python_package_cdelacombaz-0.1.dist-info/METADATA
my_first_python_package_cdelacombaz-0.1.dist-info/WHEEL
my_first_python_package_cdelacombaz-0.1.dist-info/top_level.txt
my_first_python_package_cdelacombaz-0.1.dist-info/RECORD
