Metadata-Version: 2.1
Name: my-first-python-package-cdelacombaz
Version: 0.1
Summary: Creating my first Python package
Home-page: UNKNOWN
Author: Cedric Delacombaz
Author-email: cdelacombaz@bluewin.ch
License: UNKNOWN
Platform: UNKNOWN
Classifier: Programming Language :: Python :: 3.6
